range_streams/__init__.py
range_streams/async_utils.py
range_streams/http_utils.py
range_streams/log_utils.py
range_streams/overlaps.py
range_streams/py.typed
range_streams/range_utils.py
range_streams/request.py
range_streams/response.py
range_streams/stream.py
range_streams/types.py
range_streams/codecs/__init__.py
range_streams/codecs/conda/__init__.py
range_streams/codecs/conda/stream.py
range_streams/codecs/png/__init__.py
range_streams/codecs/png/data.py
range_streams/codecs/png/reconstruct.py
range_streams/codecs/png/stream.py
range_streams/codecs/share/__init__.py
range_streams/codecs/share/data.py
range_streams/codecs/tar/__init__.py
range_streams/codecs/tar/data.py
range_streams/codecs/tar/stream.py
range_streams/codecs/zip/__init__.py
range_streams/codecs/zip/data.py
range_streams/codecs/zip/stream.py
range_streams/codecs/zstd/__init__.py
range_streams/codecs/zstd/tar.py
range_streams-1.3.0.dist-info/LICENSE
range_streams-1.3.0.dist-info/METADATA
range_streams-1.3.0.dist-info/WHEEL
range_streams-1.3.0.dist-info/top_level.txt
range_streams-1.3.0.dist-info/RECORD
