Metadata-Version: 2.1
Name: range-streams
Version: 1.3.0
Summary: Streaming via range requests.
Home-page: https://github.com/lmmx/range-streams
Author: Louis Maddox
Author-email: louismmx@gmail.com
Maintainer: Louis Maddox
Maintainer-email: louismmx@gmail.com
License: MIT
Project-URL: Documentation, https://range-streams.readthedocs.io/
Project-URL: Bug Tracker, https://github.com/lmmx/range-streams/issues
Project-URL: Source Code, https://github.com/lmmx/range-streams
Classifier: Development Status :: 4 - Beta
Classifier: Intended Audience :: Developers
Classifier: Natural Language :: English
Classifier: License :: OSI Approved :: MIT License
Classifier: Operating System :: OS Independent
Classifier: Programming Language :: Python
Classifier: Programming Language :: Python :: Implementation :: CPython
Classifier: Programming Language :: Python :: 3
Classifier: Programming Language :: Python :: 3.8
Classifier: Programming Language :: Python :: 3.9
Classifier: Topic :: Internet :: WWW/HTTP
Requires-Python: >=3.8
License-File: LICENSE
Requires-Dist: aiostream
Requires-Dist: httpx
Requires-Dist: python-ranges
Requires-Dist: pyzstd
Requires-Dist: tqdm
Provides-Extra: dev
Requires-Dist: coverage[toml] (>=5.5) ; extra == 'dev'
Requires-Dist: pytest ; extra == 'dev'
Requires-Dist: sphinx (>=4) ; extra == 'dev'
Requires-Dist: sphinx-rtd-theme ; extra == 'dev'
Requires-Dist: sphinx-autodoc-typehints ; extra == 'dev'
Requires-Dist: pre-commit ; extra == 'dev'
Provides-Extra: docs
Requires-Dist: sphinx (>=4) ; extra == 'docs'
Requires-Dist: sphinx-rtd-theme ; extra == 'docs'
Requires-Dist: sphinx-autodoc-typehints ; extra == 'docs'
Provides-Extra: tests
Requires-Dist: coverage[toml] (>=5.5) ; extra == 'tests'
Requires-Dist: pytest ; extra == 'tests'
